bibspire/__init__.py
bibspire/__main__.py
bibspire/cli.py
bibspire/core.py
bibspire-1.1.3.dist-info/licenses/LICENSE
bibspire-1.1.3.dist-info/METADATA
bibspire-1.1.3.dist-info/WHEEL
bibspire-1.1.3.dist-info/entry_points.txt
bibspire-1.1.3.dist-info/top_level.txt
bibspire-1.1.3.dist-info/RECORD
