Metadata-Version: 2.4
Name: bibspire
Version: 1.1.3
Summary: A tool to update .bib entries with INSPIRE-HEP citations
Author-email: Lorenz Gärtner <lorenz.gaertner@gmail.com>
License: MIT
Project-URL: Homepage, https://github.com/lorenzennio/bibspire
Project-URL: Bug Tracker, https://github.com/lorenzennio/bibspire/issues
Keywords: bibliography,bibtex,inspire,hep,physics
Classifier: Development Status :: 4 - Beta
Classifier: Intended Audience :: Science/Research
Classifier: Programming Language :: Python :: 3
Classifier: Programming Language :: Python :: 3.8
Classifier: Topic :: Scientific/Engineering :: Physics
Requires-Python: >=3.8
License-File: LICENSE
Requires-Dist: requests>=2.25.0
Provides-Extra: test
Requires-Dist: pytest>=6.0.0; extra == "test"
Requires-Dist: pytest-mock>=3.6.0; extra == "test"
Requires-Dist: responses>=0.21.0; extra == "test"
Requires-Dist: pytest-cov>=4.0.0; extra == "test"
Provides-Extra: dev
Requires-Dist: pytest>=6.0.0; extra == "dev"
Requires-Dist: pytest-mock>=3.6.0; extra == "dev"
Requires-Dist: responses>=0.21.0; extra == "dev"
Requires-Dist: pytest-cov>=4.0.0; extra == "dev"
Requires-Dist: build>=0.8.0; extra == "dev"
Requires-Dist: ruff>=0.1.0; extra == "dev"
Requires-Dist: twine>=4.0.0; extra == "dev"
Requires-Dist: pre-commit>=3.0.0; extra == "dev"
Dynamic: license-file
